treasmo/__init__.py
treasmo/core.py
treasmo/ds.py
treasmo/lee_vec.py
treasmo/moran_vec.py
treasmo/pl.py
treasmo/tl.py
treasmo-1.0.4.dist-info/LICENSE
treasmo-1.0.4.dist-info/METADATA
treasmo-1.0.4.dist-info/WHEEL
treasmo-1.0.4.dist-info/top_level.txt
treasmo-1.0.4.dist-info/RECORD
