Metadata-Version: 2.1
Name: treasmo
Version: 1.0.4
Summary: Transcription regulation analysis toolkit for single-cell multi-omics data
Home-page: https://github.com/ChaozhongLiu/TREASMO
Author: Chaozhong Liu
Author-email: czliubioinfo@gmail.com
Classifier: Programming Language :: Python :: 3 :: Only
Classifier: License :: OSI Approved :: GNU Affero General Public License v3
Classifier: Operating System :: OS Independent
License-File: LICENSE
